{
  "updated": "2025-10-04T11:33:51.290378",
  "headlines": [
    {
      "title": "Adani Ports shares soar 4.06% on strong market performance",
      "source": "ZORO AI",
      "time": "2025-10-04T11:33:50.858822"
    },
    {
      "title": "Infosys remains steady (+0.50%) in recent trading",
      "source": "ZORO AI",
      "time": "2025-10-04T11:33:51.055435"
    },
    {
      "title": "Wipro remains steady (+0.00%) in recent trading",
      "source": "ZORO AI",
      "time": "2025-10-04T11:33:51.206661"
    },
    {
      "title": "Reliance shares soar 9.18% on strong market performance",
      "source": "ZORO AI",
      "time": "2025-10-04T11:33:51.290329"
    },
    {
      "title": "Infosys launches new product line",
      "source": "ZORO AI",
      "time": "2025-10-04T11:33:51.290346"
    },
    {
      "title": "Infosys announces merger deal",
      "source": "ZORO AI",
      "time": "2025-10-04T11:33:51.290350"
    },
    {
      "title": "Infosys launches new product line",
      "source": "ZORO AI",
      "time": "2025-10-04T11:33:51.290354"
    },
    {
      "title": "Tata Motors faces regulatory pipeline delays",
      "source": "ZORO AI",
      "time": "2025-10-04T11:33:51.290362"
    },
    {
      "title": "Tata Motors faces regulatory pipeline delays",
      "source": "ZORO AI",
      "time": "2025-10-04T11:33:51.290368"
    },
    {
      "title": "Wipro launches new product line",
      "source": "ZORO AI",
      "time": "2025-10-04T11:33:51.290375"
    }
  ]
}