{
  "updated": "2025-11-04T23:56:52.875218",
  "headlines": [
    {
      "title": "Adani Ports remains steady (-0.87%) in recent trading",
      "source": "ZORO AI",
      "time": "2025-11-04T23:56:52.447737"
    },
    {
      "title": "Infosys remains steady (-0.67%) in recent trading",
      "source": "ZORO AI",
      "time": "2025-11-04T23:56:52.609545"
    },
    {
      "title": "Wipro remains steady (-1.15%) in recent trading",
      "source": "ZORO AI",
      "time": "2025-11-04T23:56:52.747063"
    },
    {
      "title": "Reliance shares plunge -9.41% amid market sell\u2011off",
      "source": "ZORO AI",
      "time": "2025-11-04T23:56:52.875165"
    },
    {
      "title": "Adani Ports launches new product line",
      "source": "ZORO AI",
      "time": "2025-11-04T23:56:52.875182"
    },
    {
      "title": "Wipro announces merger deal",
      "source": "ZORO AI",
      "time": "2025-11-04T23:56:52.875189"
    },
    {
      "title": "Infosys announces merger deal",
      "source": "ZORO AI",
      "time": "2025-11-04T23:56:52.875196"
    },
    {
      "title": "Infosys faces regulatory pipeline delays",
      "source": "ZORO AI",
      "time": "2025-11-04T23:56:52.875205"
    },
    {
      "title": "Infosys faces regulatory pipeline delays",
      "source": "ZORO AI",
      "time": "2025-11-04T23:56:52.875210"
    },
    {
      "title": "Reliance faces regulatory pipeline delays",
      "source": "ZORO AI",
      "time": "2025-11-04T23:56:52.875216"
    }
  ]
}