{
  "updated": "2025-11-15T04:46:37.022215",
  "headlines": [
    {
      "title": "Adani Ports shares plunge -5.34% amid market sell\u2011off",
      "source": "ZORO AI",
      "time": "2025-11-15T04:46:36.105960"
    },
    {
      "title": "Infosys remains steady (-1.83%) in recent trading",
      "source": "ZORO AI",
      "time": "2025-11-15T04:46:36.524418"
    },
    {
      "title": "Wipro remains steady (-0.38%) in recent trading",
      "source": "ZORO AI",
      "time": "2025-11-15T04:46:36.801818"
    },
    {
      "title": "Reliance shares plunge -4.86% amid market sell\u2011off",
      "source": "ZORO AI",
      "time": "2025-11-15T04:46:37.022161"
    },
    {
      "title": "Wipro announces merger deal",
      "source": "ZORO AI",
      "time": "2025-11-15T04:46:37.022177"
    },
    {
      "title": "Wipro faces regulatory pipeline delays",
      "source": "ZORO AI",
      "time": "2025-11-15T04:46:37.022182"
    },
    {
      "title": "Adani Ports announces merger deal",
      "source": "ZORO AI",
      "time": "2025-11-15T04:46:37.022194"
    },
    {
      "title": "Reliance faces regulatory pipeline delays",
      "source": "ZORO AI",
      "time": "2025-11-15T04:46:37.022202"
    },
    {
      "title": "Infosys launches new product line",
      "source": "ZORO AI",
      "time": "2025-11-15T04:46:37.022208"
    },
    {
      "title": "Reliance faces regulatory pipeline delays",
      "source": "ZORO AI",
      "time": "2025-11-15T04:46:37.022213"
    }
  ]
}