{
  "updated": "2025-10-04T03:06:35.272372",
  "headlines": [
    {
      "title": "Adani Ports shares soar 4.06% on strong market performance",
      "source": "ZORO AI",
      "time": "2025-10-04T03:06:34.766693"
    },
    {
      "title": "Infosys remains steady (+0.50%) in recent trading",
      "source": "ZORO AI",
      "time": "2025-10-04T03:06:34.968998"
    },
    {
      "title": "Wipro remains steady (+0.00%) in recent trading",
      "source": "ZORO AI",
      "time": "2025-10-04T03:06:35.170090"
    },
    {
      "title": "Reliance shares soar 9.18% on strong market performance",
      "source": "ZORO AI",
      "time": "2025-10-04T03:06:35.272331"
    },
    {
      "title": "Wipro faces regulatory pipeline delays",
      "source": "ZORO AI",
      "time": "2025-10-04T03:06:35.272347"
    },
    {
      "title": "Infosys announces merger deal",
      "source": "ZORO AI",
      "time": "2025-10-04T03:06:35.272352"
    },
    {
      "title": "Infosys announces merger deal",
      "source": "ZORO AI",
      "time": "2025-10-04T03:06:35.272355"
    },
    {
      "title": "Reliance faces regulatory pipeline delays",
      "source": "ZORO AI",
      "time": "2025-10-04T03:06:35.272360"
    },
    {
      "title": "Adani Ports launches new product line",
      "source": "ZORO AI",
      "time": "2025-10-04T03:06:35.272363"
    },
    {
      "title": "Tata Motors faces regulatory pipeline delays",
      "source": "ZORO AI",
      "time": "2025-10-04T03:06:35.272368"
    }
  ]
}