{
  "updated": "2026-01-09T00:00:28.917899",
  "headlines": [
    {
      "title": "Adani Ports shares soar 5.22% on strong market performance",
      "source": "ZORO AI",
      "time": "2026-01-09T00:00:28.040616"
    },
    {
      "title": "Infosys remains steady (-1.04%) in recent trading",
      "source": "ZORO AI",
      "time": "2026-01-09T00:00:28.326743"
    },
    {
      "title": "Wipro remains steady (-0.68%) in recent trading",
      "source": "ZORO AI",
      "time": "2026-01-09T00:00:28.673272"
    },
    {
      "title": "Reliance remains steady (-1.75%) in recent trading",
      "source": "ZORO AI",
      "time": "2026-01-09T00:00:28.917846"
    },
    {
      "title": "Infosys launches new product line",
      "source": "ZORO AI",
      "time": "2026-01-09T00:00:28.917867"
    },
    {
      "title": "Tata Motors launches new product line",
      "source": "ZORO AI",
      "time": "2026-01-09T00:00:28.917874"
    },
    {
      "title": "Adani Ports faces regulatory pipeline delays",
      "source": "ZORO AI",
      "time": "2026-01-09T00:00:28.917879"
    },
    {
      "title": "Adani Ports announces merger deal",
      "source": "ZORO AI",
      "time": "2026-01-09T00:00:28.917886"
    },
    {
      "title": "Wipro announces merger deal",
      "source": "ZORO AI",
      "time": "2026-01-09T00:00:28.917892"
    },
    {
      "title": "Tata Motors launches new product line",
      "source": "ZORO AI",
      "time": "2026-01-09T00:00:28.917897"
    }
  ]
}