{
  "updated": "2025-08-16T14:58:41.552684",
  "headlines": [
    {
      "title": "Adani Ports remains steady (-1.38%) in recent trading",
      "source": "ZORO AI",
      "time": "2025-08-16T14:58:41.162712"
    },
    {
      "title": "Infosys remains steady (+1.22%) in recent trading",
      "source": "ZORO AI",
      "time": "2025-08-16T14:58:41.314890"
    },
    {
      "title": "Wipro remains steady (+0.74%) in recent trading",
      "source": "ZORO AI",
      "time": "2025-08-16T14:58:41.471016"
    },
    {
      "title": "Reliance remains steady (+2.91%) in recent trading",
      "source": "ZORO AI",
      "time": "2025-08-16T14:58:41.552631"
    },
    {
      "title": "Infosys launches new product line",
      "source": "ZORO AI",
      "time": "2025-08-16T14:58:41.552650"
    },
    {
      "title": "Wipro launches new product line",
      "source": "ZORO AI",
      "time": "2025-08-16T14:58:41.552656"
    },
    {
      "title": "Infosys launches new product line",
      "source": "ZORO AI",
      "time": "2025-08-16T14:58:41.552661"
    },
    {
      "title": "Infosys announces merger deal",
      "source": "ZORO AI",
      "time": "2025-08-16T14:58:41.552669"
    },
    {
      "title": "Wipro faces regulatory pipeline delays",
      "source": "ZORO AI",
      "time": "2025-08-16T14:58:41.552676"
    },
    {
      "title": "Infosys faces regulatory pipeline delays",
      "source": "ZORO AI",
      "time": "2025-08-16T14:58:41.552680"
    }
  ]
}