{
  "updated": "2025-08-29T02:42:03.471169",
  "headlines": [
    {
      "title": "Adani Ports remains steady (-1.88%) in recent trading",
      "source": "ZORO AI",
      "time": "2025-08-29T02:42:02.891339"
    },
    {
      "title": "Infosys remains steady (-2.07%) in recent trading",
      "source": "ZORO AI",
      "time": "2025-08-29T02:42:03.052627"
    },
    {
      "title": "Wipro remains steady (-0.36%) in recent trading",
      "source": "ZORO AI",
      "time": "2025-08-29T02:42:03.291032"
    },
    {
      "title": "Reliance remains steady (+0.42%) in recent trading",
      "source": "ZORO AI",
      "time": "2025-08-29T02:42:03.471117"
    },
    {
      "title": "Tata Motors faces regulatory pipeline delays",
      "source": "ZORO AI",
      "time": "2025-08-29T02:42:03.471136"
    },
    {
      "title": "Adani Ports faces regulatory pipeline delays",
      "source": "ZORO AI",
      "time": "2025-08-29T02:42:03.471144"
    },
    {
      "title": "Infosys faces regulatory pipeline delays",
      "source": "ZORO AI",
      "time": "2025-08-29T02:42:03.471149"
    },
    {
      "title": "Reliance launches new product line",
      "source": "ZORO AI",
      "time": "2025-08-29T02:42:03.471156"
    },
    {
      "title": "Wipro announces merger deal",
      "source": "ZORO AI",
      "time": "2025-08-29T02:42:03.471161"
    },
    {
      "title": "Adani Ports faces regulatory pipeline delays",
      "source": "ZORO AI",
      "time": "2025-08-29T02:42:03.471166"
    }
  ]
}