{
  "updated": "2025-07-31T23:18:48.836340",
  "headlines": [
    {
      "title": "Adani Ports remains steady (+0.05%) in recent trading",
      "source": "ZORO AI",
      "time": "2025-07-31T23:18:48.405556"
    },
    {
      "title": "Infosys remains steady (-1.36%) in recent trading",
      "source": "ZORO AI",
      "time": "2025-07-31T23:18:48.590364"
    },
    {
      "title": "Wipro remains steady (-1.09%) in recent trading",
      "source": "ZORO AI",
      "time": "2025-07-31T23:18:48.736626"
    },
    {
      "title": "Reliance shares plunge -16.41% amid market sell\u2011off",
      "source": "ZORO AI",
      "time": "2025-07-31T23:18:48.836285"
    },
    {
      "title": "Infosys launches new product line",
      "source": "ZORO AI",
      "time": "2025-07-31T23:18:48.836305"
    },
    {
      "title": "Reliance launches new product line",
      "source": "ZORO AI",
      "time": "2025-07-31T23:18:48.836313"
    },
    {
      "title": "Tata Motors announces merger deal",
      "source": "ZORO AI",
      "time": "2025-07-31T23:18:48.836319"
    },
    {
      "title": "Adani Ports announces merger deal",
      "source": "ZORO AI",
      "time": "2025-07-31T23:18:48.836327"
    },
    {
      "title": "Reliance announces merger deal",
      "source": "ZORO AI",
      "time": "2025-07-31T23:18:48.836333"
    },
    {
      "title": "Adani Ports announces merger deal",
      "source": "ZORO AI",
      "time": "2025-07-31T23:18:48.836337"
    }
  ]
}