{
  "updated": "2025-10-06T23:29:39.750537",
  "headlines": [
    {
      "title": "Adani Ports remains steady (-0.35%) in recent trading",
      "source": "ZORO AI",
      "time": "2025-10-06T23:29:39.223321"
    },
    {
      "title": "Infosys remains steady (+2.83%) in recent trading",
      "source": "ZORO AI",
      "time": "2025-10-06T23:29:39.381928"
    },
    {
      "title": "Wipro remains steady (+1.53%) in recent trading",
      "source": "ZORO AI",
      "time": "2025-10-06T23:29:39.618618"
    },
    {
      "title": "Reliance remains steady (+0.00%) in recent trading",
      "source": "ZORO AI",
      "time": "2025-10-06T23:29:39.750500"
    },
    {
      "title": "Reliance faces regulatory pipeline delays",
      "source": "ZORO AI",
      "time": "2025-10-06T23:29:39.750516"
    },
    {
      "title": "Tata Motors launches new product line",
      "source": "ZORO AI",
      "time": "2025-10-06T23:29:39.750520"
    },
    {
      "title": "Adani Ports launches new product line",
      "source": "ZORO AI",
      "time": "2025-10-06T23:29:39.750524"
    },
    {
      "title": "Adani Ports faces regulatory pipeline delays",
      "source": "ZORO AI",
      "time": "2025-10-06T23:29:39.750529"
    },
    {
      "title": "Reliance launches new product line",
      "source": "ZORO AI",
      "time": "2025-10-06T23:29:39.750532"
    },
    {
      "title": "Reliance faces regulatory pipeline delays",
      "source": "ZORO AI",
      "time": "2025-10-06T23:29:39.750535"
    }
  ]
}