{
  "updated": "2025-12-24T16:32:53.462439",
  "headlines": [
    {
      "title": "Adani Ports remains steady (+0.67%) in recent trading",
      "source": "ZORO AI",
      "time": "2025-12-24T16:32:53.050979"
    },
    {
      "title": "Infosys remains steady (-0.13%) in recent trading",
      "source": "ZORO AI",
      "time": "2025-12-24T16:32:53.213425"
    },
    {
      "title": "Wipro remains steady (-1.85%) in recent trading",
      "source": "ZORO AI",
      "time": "2025-12-24T16:32:53.376025"
    },
    {
      "title": "Reliance shares plunge -3.54% amid market sell\u2011off",
      "source": "ZORO AI",
      "time": "2025-12-24T16:32:53.462389"
    },
    {
      "title": "Adani Ports launches new product line",
      "source": "ZORO AI",
      "time": "2025-12-24T16:32:53.462409"
    },
    {
      "title": "Adani Ports announces merger deal",
      "source": "ZORO AI",
      "time": "2025-12-24T16:32:53.462416"
    },
    {
      "title": "Tata Motors announces merger deal",
      "source": "ZORO AI",
      "time": "2025-12-24T16:32:53.462421"
    },
    {
      "title": "Wipro faces regulatory pipeline delays",
      "source": "ZORO AI",
      "time": "2025-12-24T16:32:53.462428"
    },
    {
      "title": "Reliance faces regulatory pipeline delays",
      "source": "ZORO AI",
      "time": "2025-12-24T16:32:53.462433"
    },
    {
      "title": "Reliance announces merger deal",
      "source": "ZORO AI",
      "time": "2025-12-24T16:32:53.462437"
    }
  ]
}