{
  "updated": "2025-12-04T08:38:31.360467",
  "headlines": [
    {
      "title": "Adani Ports remains steady (+1.96%) in recent trading",
      "source": "ZORO AI",
      "time": "2025-12-04T08:38:30.663058"
    },
    {
      "title": "Infosys remains steady (+1.44%) in recent trading",
      "source": "ZORO AI",
      "time": "2025-12-04T08:38:30.968668"
    },
    {
      "title": "Wipro remains steady (+1.47%) in recent trading",
      "source": "ZORO AI",
      "time": "2025-12-04T08:38:31.190741"
    },
    {
      "title": "Reliance shares soar 3.38% on strong market performance",
      "source": "ZORO AI",
      "time": "2025-12-04T08:38:31.360420"
    },
    {
      "title": "Tata Motors faces regulatory pipeline delays",
      "source": "ZORO AI",
      "time": "2025-12-04T08:38:31.360435"
    },
    {
      "title": "Reliance announces merger deal",
      "source": "ZORO AI",
      "time": "2025-12-04T08:38:31.360440"
    },
    {
      "title": "Infosys launches new product line",
      "source": "ZORO AI",
      "time": "2025-12-04T08:38:31.360444"
    },
    {
      "title": "Reliance launches new product line",
      "source": "ZORO AI",
      "time": "2025-12-04T08:38:31.360452"
    },
    {
      "title": "Adani Ports faces regulatory pipeline delays",
      "source": "ZORO AI",
      "time": "2025-12-04T08:38:31.360458"
    },
    {
      "title": "Reliance announces merger deal",
      "source": "ZORO AI",
      "time": "2025-12-04T08:38:31.360464"
    }
  ]
}