{
  "updated": "2025-09-09T15:32:54.398711",
  "headlines": [
    {
      "title": "Adani Ports remains steady (-0.90%) in recent trading",
      "source": "ZORO AI",
      "time": "2025-09-09T15:32:53.952613"
    },
    {
      "title": "Infosys remains steady (+1.64%) in recent trading",
      "source": "ZORO AI",
      "time": "2025-09-09T15:32:54.122812"
    },
    {
      "title": "Wipro remains steady (+0.55%) in recent trading",
      "source": "ZORO AI",
      "time": "2025-09-09T15:32:54.283570"
    },
    {
      "title": "Reliance shares plunge -3.61% amid market sell\u2011off",
      "source": "ZORO AI",
      "time": "2025-09-09T15:32:54.398674"
    },
    {
      "title": "Infosys launches new product line",
      "source": "ZORO AI",
      "time": "2025-09-09T15:32:54.398689"
    },
    {
      "title": "Infosys faces regulatory pipeline delays",
      "source": "ZORO AI",
      "time": "2025-09-09T15:32:54.398694"
    },
    {
      "title": "Infosys faces regulatory pipeline delays",
      "source": "ZORO AI",
      "time": "2025-09-09T15:32:54.398698"
    },
    {
      "title": "Adani Ports launches new product line",
      "source": "ZORO AI",
      "time": "2025-09-09T15:32:54.398703"
    },
    {
      "title": "Adani Ports launches new product line",
      "source": "ZORO AI",
      "time": "2025-09-09T15:32:54.398706"
    },
    {
      "title": "Wipro faces regulatory pipeline delays",
      "source": "ZORO AI",
      "time": "2025-09-09T15:32:54.398709"
    }
  ]
}