{
  "updated": "2026-01-18T12:48:56.762221",
  "headlines": [
    {
      "title": "Adani Ports shares plunge -5.89% amid market sell\u2011off",
      "source": "ZORO AI",
      "time": "2026-01-18T12:48:56.364111"
    },
    {
      "title": "Infosys remains steady (-1.01%) in recent trading",
      "source": "ZORO AI",
      "time": "2026-01-18T12:48:56.519394"
    },
    {
      "title": "Wipro shares plunge -7.41% amid market sell\u2011off",
      "source": "ZORO AI",
      "time": "2026-01-18T12:48:56.668631"
    },
    {
      "title": "Reliance remains steady (-2.12%) in recent trading",
      "source": "ZORO AI",
      "time": "2026-01-18T12:48:56.762186"
    },
    {
      "title": "Infosys announces merger deal",
      "source": "ZORO AI",
      "time": "2026-01-18T12:48:56.762201"
    },
    {
      "title": "Infosys faces regulatory pipeline delays",
      "source": "ZORO AI",
      "time": "2026-01-18T12:48:56.762206"
    },
    {
      "title": "Tata Motors launches new product line",
      "source": "ZORO AI",
      "time": "2026-01-18T12:48:56.762209"
    },
    {
      "title": "Reliance faces regulatory pipeline delays",
      "source": "ZORO AI",
      "time": "2026-01-18T12:48:56.762214"
    },
    {
      "title": "Wipro announces merger deal",
      "source": "ZORO AI",
      "time": "2026-01-18T12:48:56.762217"
    },
    {
      "title": "Infosys launches new product line",
      "source": "ZORO AI",
      "time": "2026-01-18T12:48:56.762220"
    }
  ]
}