{
  "updated": "2025-06-20T22:16:17.054127",
  "headlines": [
    {
      "title": "Adani Ports remains steady (-0.11%) in recent trading",
      "source": "ZORO AI",
      "time": "2025-06-20T22:16:16.685460"
    },
    {
      "title": "Infosys shares plunge -4.07% amid market sell\u2011off",
      "source": "ZORO AI",
      "time": "2025-06-20T22:16:16.827326"
    },
    {
      "title": "Wipro remains steady (-0.34%) in recent trading",
      "source": "ZORO AI",
      "time": "2025-06-20T22:16:16.971760"
    },
    {
      "title": "Reliance shares plunge -15.41% amid market sell\u2011off",
      "source": "ZORO AI",
      "time": "2025-06-20T22:16:17.054075"
    },
    {
      "title": "Reliance launches new product line",
      "source": "ZORO AI",
      "time": "2025-06-20T22:16:17.054093"
    },
    {
      "title": "Adani Ports faces regulatory pipeline delays",
      "source": "ZORO AI",
      "time": "2025-06-20T22:16:17.054101"
    },
    {
      "title": "Wipro launches new product line",
      "source": "ZORO AI",
      "time": "2025-06-20T22:16:17.054107"
    },
    {
      "title": "Adani Ports launches new product line",
      "source": "ZORO AI",
      "time": "2025-06-20T22:16:17.054115"
    },
    {
      "title": "Tata Motors announces merger deal",
      "source": "ZORO AI",
      "time": "2025-06-20T22:16:17.054120"
    },
    {
      "title": "Tata Motors launches new product line",
      "source": "ZORO AI",
      "time": "2025-06-20T22:16:17.054125"
    }
  ]
}