{
  "updated": "2025-10-15T03:58:49.929458",
  "headlines": [
    {
      "title": "Adani Ports remains steady (+1.95%) in recent trading",
      "source": "ZORO AI",
      "time": "2025-10-15T03:58:49.568138"
    },
    {
      "title": "Infosys remains steady (-1.79%) in recent trading",
      "source": "ZORO AI",
      "time": "2025-10-15T03:58:49.709414"
    },
    {
      "title": "Wipro remains steady (+1.49%) in recent trading",
      "source": "ZORO AI",
      "time": "2025-10-15T03:58:49.858811"
    },
    {
      "title": "Reliance remains steady (-2.56%) in recent trading",
      "source": "ZORO AI",
      "time": "2025-10-15T03:58:49.929423"
    },
    {
      "title": "Reliance faces regulatory pipeline delays",
      "source": "ZORO AI",
      "time": "2025-10-15T03:58:49.929438"
    },
    {
      "title": "Tata Motors announces merger deal",
      "source": "ZORO AI",
      "time": "2025-10-15T03:58:49.929443"
    },
    {
      "title": "Tata Motors launches new product line",
      "source": "ZORO AI",
      "time": "2025-10-15T03:58:49.929446"
    },
    {
      "title": "Tata Motors faces regulatory pipeline delays",
      "source": "ZORO AI",
      "time": "2025-10-15T03:58:49.929451"
    },
    {
      "title": "Wipro launches new product line",
      "source": "ZORO AI",
      "time": "2025-10-15T03:58:49.929454"
    },
    {
      "title": "Tata Motors faces regulatory pipeline delays",
      "source": "ZORO AI",
      "time": "2025-10-15T03:58:49.929457"
    }
  ]
}