{
  "updated": "2026-01-07T09:59:21.893694",
  "headlines": [
    {
      "title": "Adani Ports remains steady (+0.62%) in recent trading",
      "source": "ZORO AI",
      "time": "2026-01-07T09:59:21.479460"
    },
    {
      "title": "Infosys remains steady (+2.38%) in recent trading",
      "source": "ZORO AI",
      "time": "2026-01-07T09:59:21.647837"
    },
    {
      "title": "Wipro remains steady (+1.40%) in recent trading",
      "source": "ZORO AI",
      "time": "2026-01-07T09:59:21.800394"
    },
    {
      "title": "Reliance shares soar 7.99% on strong market performance",
      "source": "ZORO AI",
      "time": "2026-01-07T09:59:21.893642"
    },
    {
      "title": "Tata Motors launches new product line",
      "source": "ZORO AI",
      "time": "2026-01-07T09:59:21.893661"
    },
    {
      "title": "Reliance launches new product line",
      "source": "ZORO AI",
      "time": "2026-01-07T09:59:21.893667"
    },
    {
      "title": "Wipro launches new product line",
      "source": "ZORO AI",
      "time": "2026-01-07T09:59:21.893672"
    },
    {
      "title": "Reliance faces regulatory pipeline delays",
      "source": "ZORO AI",
      "time": "2026-01-07T09:59:21.893679"
    },
    {
      "title": "Infosys faces regulatory pipeline delays",
      "source": "ZORO AI",
      "time": "2026-01-07T09:59:21.893686"
    },
    {
      "title": "Tata Motors faces regulatory pipeline delays",
      "source": "ZORO AI",
      "time": "2026-01-07T09:59:21.893692"
    }
  ]
}