{
  "updated": "2025-12-10T20:44:15.730144",
  "headlines": [
    {
      "title": "Adani Ports remains steady (+1.76%) in recent trading",
      "source": "ZORO AI",
      "time": "2025-12-10T20:44:15.147478"
    },
    {
      "title": "Infosys remains steady (+2.00%) in recent trading",
      "source": "ZORO AI",
      "time": "2025-12-10T20:44:15.389461"
    },
    {
      "title": "Wipro remains steady (+1.05%) in recent trading",
      "source": "ZORO AI",
      "time": "2025-12-10T20:44:15.573281"
    },
    {
      "title": "Reliance shares plunge -5.74% amid market sell\u2011off",
      "source": "ZORO AI",
      "time": "2025-12-10T20:44:15.730108"
    },
    {
      "title": "Wipro announces merger deal",
      "source": "ZORO AI",
      "time": "2025-12-10T20:44:15.730124"
    },
    {
      "title": "Tata Motors launches new product line",
      "source": "ZORO AI",
      "time": "2025-12-10T20:44:15.730128"
    },
    {
      "title": "Infosys announces merger deal",
      "source": "ZORO AI",
      "time": "2025-12-10T20:44:15.730131"
    },
    {
      "title": "Infosys launches new product line",
      "source": "ZORO AI",
      "time": "2025-12-10T20:44:15.730136"
    },
    {
      "title": "Adani Ports launches new product line",
      "source": "ZORO AI",
      "time": "2025-12-10T20:44:15.730140"
    },
    {
      "title": "Wipro faces regulatory pipeline delays",
      "source": "ZORO AI",
      "time": "2025-12-10T20:44:15.730143"
    }
  ]
}