{
  "updated": "2025-09-07T06:51:12.906631",
  "headlines": [
    {
      "title": "Adani Ports remains steady (+0.53%) in recent trading",
      "source": "ZORO AI",
      "time": "2025-09-07T06:51:12.544748"
    },
    {
      "title": "Infosys remains steady (-1.27%) in recent trading",
      "source": "ZORO AI",
      "time": "2025-09-07T06:51:12.695134"
    },
    {
      "title": "Wipro remains steady (+0.00%) in recent trading",
      "source": "ZORO AI",
      "time": "2025-09-07T06:51:12.830980"
    },
    {
      "title": "Reliance remains steady (+0.24%) in recent trading",
      "source": "ZORO AI",
      "time": "2025-09-07T06:51:12.906577"
    },
    {
      "title": "Adani Ports launches new product line",
      "source": "ZORO AI",
      "time": "2025-09-07T06:51:12.906597"
    },
    {
      "title": "Tata Motors faces regulatory pipeline delays",
      "source": "ZORO AI",
      "time": "2025-09-07T06:51:12.906605"
    },
    {
      "title": "Tata Motors announces merger deal",
      "source": "ZORO AI",
      "time": "2025-09-07T06:51:12.906612"
    },
    {
      "title": "Tata Motors launches new product line",
      "source": "ZORO AI",
      "time": "2025-09-07T06:51:12.906619"
    },
    {
      "title": "Adani Ports launches new product line",
      "source": "ZORO AI",
      "time": "2025-09-07T06:51:12.906624"
    },
    {
      "title": "Infosys faces regulatory pipeline delays",
      "source": "ZORO AI",
      "time": "2025-09-07T06:51:12.906628"
    }
  ]
}