{
  "updated": "2026-01-03T18:55:00.597110",
  "headlines": [
    {
      "title": "Adani Ports remains steady (-0.68%) in recent trading",
      "source": "ZORO AI",
      "time": "2026-01-03T18:55:00.203232"
    },
    {
      "title": "Infosys remains steady (+1.85%) in recent trading",
      "source": "ZORO AI",
      "time": "2026-01-03T18:55:00.369838"
    },
    {
      "title": "Wipro remains steady (+2.82%) in recent trading",
      "source": "ZORO AI",
      "time": "2026-01-03T18:55:00.513978"
    },
    {
      "title": "Reliance shares soar 5.28% on strong market performance",
      "source": "ZORO AI",
      "time": "2026-01-03T18:55:00.597075"
    },
    {
      "title": "Wipro announces merger deal",
      "source": "ZORO AI",
      "time": "2026-01-03T18:55:00.597090"
    },
    {
      "title": "Reliance announces merger deal",
      "source": "ZORO AI",
      "time": "2026-01-03T18:55:00.597094"
    },
    {
      "title": "Reliance announces merger deal",
      "source": "ZORO AI",
      "time": "2026-01-03T18:55:00.597097"
    },
    {
      "title": "Tata Motors announces merger deal",
      "source": "ZORO AI",
      "time": "2026-01-03T18:55:00.597102"
    },
    {
      "title": "Adani Ports launches new product line",
      "source": "ZORO AI",
      "time": "2026-01-03T18:55:00.597105"
    },
    {
      "title": "Wipro faces regulatory pipeline delays",
      "source": "ZORO AI",
      "time": "2026-01-03T18:55:00.597108"
    }
  ]
}