{
  "updated": "2025-06-24T07:51:00.548329",
  "headlines": [
    {
      "title": "Adani Ports remains steady (+0.42%) in recent trading",
      "source": "ZORO AI",
      "time": "2025-06-24T07:50:59.794464"
    },
    {
      "title": "Infosys remains steady (+2.38%) in recent trading",
      "source": "ZORO AI",
      "time": "2025-06-24T07:51:00.028849"
    },
    {
      "title": "Wipro remains steady (+1.68%) in recent trading",
      "source": "ZORO AI",
      "time": "2025-06-24T07:51:00.313117"
    },
    {
      "title": "Reliance shares plunge -23.08% amid market sell\u2011off",
      "source": "ZORO AI",
      "time": "2025-06-24T07:51:00.548273"
    },
    {
      "title": "Wipro announces merger deal",
      "source": "ZORO AI",
      "time": "2025-06-24T07:51:00.548292"
    },
    {
      "title": "Wipro launches new product line",
      "source": "ZORO AI",
      "time": "2025-06-24T07:51:00.548300"
    },
    {
      "title": "Infosys faces regulatory pipeline delays",
      "source": "ZORO AI",
      "time": "2025-06-24T07:51:00.548306"
    },
    {
      "title": "Adani Ports faces regulatory pipeline delays",
      "source": "ZORO AI",
      "time": "2025-06-24T07:51:00.548315"
    },
    {
      "title": "Reliance announces merger deal",
      "source": "ZORO AI",
      "time": "2025-06-24T07:51:00.548321"
    },
    {
      "title": "Tata Motors faces regulatory pipeline delays",
      "source": "ZORO AI",
      "time": "2025-06-24T07:51:00.548326"
    }
  ]
}