{
  "updated": "2025-11-28T23:39:38.975193",
  "headlines": [
    {
      "title": "Adani Ports remains steady (-0.71%) in recent trading",
      "source": "ZORO AI",
      "time": "2025-11-28T23:39:38.601870"
    },
    {
      "title": "Infosys remains steady (+0.34%) in recent trading",
      "source": "ZORO AI",
      "time": "2025-11-28T23:39:38.761538"
    },
    {
      "title": "Wipro remains steady (+1.12%) in recent trading",
      "source": "ZORO AI",
      "time": "2025-11-28T23:39:38.892845"
    },
    {
      "title": "Reliance remains steady (-0.09%) in recent trading",
      "source": "ZORO AI",
      "time": "2025-11-28T23:39:38.975136"
    },
    {
      "title": "Adani Ports announces merger deal",
      "source": "ZORO AI",
      "time": "2025-11-28T23:39:38.975156"
    },
    {
      "title": "Reliance faces regulatory pipeline delays",
      "source": "ZORO AI",
      "time": "2025-11-28T23:39:38.975165"
    },
    {
      "title": "Reliance launches new product line",
      "source": "ZORO AI",
      "time": "2025-11-28T23:39:38.975171"
    },
    {
      "title": "Tata Motors announces merger deal",
      "source": "ZORO AI",
      "time": "2025-11-28T23:39:38.975179"
    },
    {
      "title": "Infosys announces merger deal",
      "source": "ZORO AI",
      "time": "2025-11-28T23:39:38.975185"
    },
    {
      "title": "Wipro announces merger deal",
      "source": "ZORO AI",
      "time": "2025-11-28T23:39:38.975190"
    }
  ]
}