{
  "updated": "2026-01-17T23:45:45.327903",
  "headlines": [
    {
      "title": "Adani Ports shares plunge -5.89% amid market sell\u2011off",
      "source": "ZORO AI",
      "time": "2026-01-17T23:45:44.574510"
    },
    {
      "title": "Infosys remains steady (-1.01%) in recent trading",
      "source": "ZORO AI",
      "time": "2026-01-17T23:45:44.807391"
    },
    {
      "title": "Wipro shares plunge -7.41% amid market sell\u2011off",
      "source": "ZORO AI",
      "time": "2026-01-17T23:45:45.082800"
    },
    {
      "title": "Reliance remains steady (-2.12%) in recent trading",
      "source": "ZORO AI",
      "time": "2026-01-17T23:45:45.327859"
    },
    {
      "title": "Wipro announces merger deal",
      "source": "ZORO AI",
      "time": "2026-01-17T23:45:45.327874"
    },
    {
      "title": "Infosys faces regulatory pipeline delays",
      "source": "ZORO AI",
      "time": "2026-01-17T23:45:45.327880"
    },
    {
      "title": "Infosys launches new product line",
      "source": "ZORO AI",
      "time": "2026-01-17T23:45:45.327885"
    },
    {
      "title": "Adani Ports launches new product line",
      "source": "ZORO AI",
      "time": "2026-01-17T23:45:45.327892"
    },
    {
      "title": "Wipro launches new product line",
      "source": "ZORO AI",
      "time": "2026-01-17T23:45:45.327897"
    },
    {
      "title": "Wipro launches new product line",
      "source": "ZORO AI",
      "time": "2026-01-17T23:45:45.327901"
    }
  ]
}