{
  "updated": "2025-08-10T15:10:59.261729",
  "headlines": [
    {
      "title": "Adani Ports shares plunge -3.30% amid market sell\u2011off",
      "source": "ZORO AI",
      "time": "2025-08-10T15:10:58.831739"
    },
    {
      "title": "Infosys remains steady (-0.19%) in recent trading",
      "source": "ZORO AI",
      "time": "2025-08-10T15:10:58.965755"
    },
    {
      "title": "Wipro remains steady (+0.00%) in recent trading",
      "source": "ZORO AI",
      "time": "2025-08-10T15:10:59.147309"
    },
    {
      "title": "Reliance remains steady (-0.97%) in recent trading",
      "source": "ZORO AI",
      "time": "2025-08-10T15:10:59.261676"
    },
    {
      "title": "Infosys launches new product line",
      "source": "ZORO AI",
      "time": "2025-08-10T15:10:59.261696"
    },
    {
      "title": "Tata Motors faces regulatory pipeline delays",
      "source": "ZORO AI",
      "time": "2025-08-10T15:10:59.261703"
    },
    {
      "title": "Tata Motors announces merger deal",
      "source": "ZORO AI",
      "time": "2025-08-10T15:10:59.261708"
    },
    {
      "title": "Infosys faces regulatory pipeline delays",
      "source": "ZORO AI",
      "time": "2025-08-10T15:10:59.261716"
    },
    {
      "title": "Wipro announces merger deal",
      "source": "ZORO AI",
      "time": "2025-08-10T15:10:59.261721"
    },
    {
      "title": "Tata Motors launches new product line",
      "source": "ZORO AI",
      "time": "2025-08-10T15:10:59.261726"
    }
  ]
}