{
  "updated": "2025-10-01T23:47:38.543008",
  "headlines": [
    {
      "title": "Adani Ports remains steady (+1.33%) in recent trading",
      "source": "ZORO AI",
      "time": "2025-10-01T23:47:38.049101"
    },
    {
      "title": "Infosys remains steady (+0.61%) in recent trading",
      "source": "ZORO AI",
      "time": "2025-10-01T23:47:38.275219"
    },
    {
      "title": "Wipro remains steady (+0.00%) in recent trading",
      "source": "ZORO AI",
      "time": "2025-10-01T23:47:38.458075"
    },
    {
      "title": "Reliance remains steady (+0.83%) in recent trading",
      "source": "ZORO AI",
      "time": "2025-10-01T23:47:38.542956"
    },
    {
      "title": "Wipro announces merger deal",
      "source": "ZORO AI",
      "time": "2025-10-01T23:47:38.542975"
    },
    {
      "title": "Adani Ports faces regulatory pipeline delays",
      "source": "ZORO AI",
      "time": "2025-10-01T23:47:38.542982"
    },
    {
      "title": "Adani Ports launches new product line",
      "source": "ZORO AI",
      "time": "2025-10-01T23:47:38.542988"
    },
    {
      "title": "Tata Motors faces regulatory pipeline delays",
      "source": "ZORO AI",
      "time": "2025-10-01T23:47:38.542995"
    },
    {
      "title": "Infosys announces merger deal",
      "source": "ZORO AI",
      "time": "2025-10-01T23:47:38.543000"
    },
    {
      "title": "Reliance announces merger deal",
      "source": "ZORO AI",
      "time": "2025-10-01T23:47:38.543005"
    }
  ]
}