{
  "updated": "2025-11-07T04:22:26.363094",
  "headlines": [
    {
      "title": "Adani Ports shares plunge -5.01% amid market sell\u2011off",
      "source": "ZORO AI",
      "time": "2025-11-07T04:22:25.636856"
    },
    {
      "title": "Infosys remains steady (-1.46%) in recent trading",
      "source": "ZORO AI",
      "time": "2025-11-07T04:22:25.923510"
    },
    {
      "title": "Wipro remains steady (-0.76%) in recent trading",
      "source": "ZORO AI",
      "time": "2025-11-07T04:22:26.197498"
    },
    {
      "title": "Reliance shares plunge -3.40% amid market sell\u2011off",
      "source": "ZORO AI",
      "time": "2025-11-07T04:22:26.363058"
    },
    {
      "title": "Adani Ports announces merger deal",
      "source": "ZORO AI",
      "time": "2025-11-07T04:22:26.363074"
    },
    {
      "title": "Infosys launches new product line",
      "source": "ZORO AI",
      "time": "2025-11-07T04:22:26.363078"
    },
    {
      "title": "Reliance faces regulatory pipeline delays",
      "source": "ZORO AI",
      "time": "2025-11-07T04:22:26.363081"
    },
    {
      "title": "Reliance announces merger deal",
      "source": "ZORO AI",
      "time": "2025-11-07T04:22:26.363086"
    },
    {
      "title": "Wipro announces merger deal",
      "source": "ZORO AI",
      "time": "2025-11-07T04:22:26.363089"
    },
    {
      "title": "Reliance faces regulatory pipeline delays",
      "source": "ZORO AI",
      "time": "2025-11-07T04:22:26.363092"
    }
  ]
}