{
  "updated": "2025-08-07T18:51:47.550615",
  "headlines": [
    {
      "title": "Adani Ports remains steady (-1.22%) in recent trading",
      "source": "ZORO AI",
      "time": "2025-08-07T18:51:46.891089"
    },
    {
      "title": "Infosys remains steady (-0.37%) in recent trading",
      "source": "ZORO AI",
      "time": "2025-08-07T18:51:47.112064"
    },
    {
      "title": "Wipro remains steady (+0.57%) in recent trading",
      "source": "ZORO AI",
      "time": "2025-08-07T18:51:47.321821"
    },
    {
      "title": "Reliance remains steady (-0.49%) in recent trading",
      "source": "ZORO AI",
      "time": "2025-08-07T18:51:47.550560"
    },
    {
      "title": "Adani Ports announces merger deal",
      "source": "ZORO AI",
      "time": "2025-08-07T18:51:47.550580"
    },
    {
      "title": "Reliance launches new product line",
      "source": "ZORO AI",
      "time": "2025-08-07T18:51:47.550585"
    },
    {
      "title": "Wipro faces regulatory pipeline delays",
      "source": "ZORO AI",
      "time": "2025-08-07T18:51:47.550591"
    },
    {
      "title": "Reliance faces regulatory pipeline delays",
      "source": "ZORO AI",
      "time": "2025-08-07T18:51:47.550600"
    },
    {
      "title": "Tata Motors announces merger deal",
      "source": "ZORO AI",
      "time": "2025-08-07T18:51:47.550606"
    },
    {
      "title": "Adani Ports faces regulatory pipeline delays",
      "source": "ZORO AI",
      "time": "2025-08-07T18:51:47.550612"
    }
  ]
}