{
  "updated": "2025-10-17T19:07:46.402288",
  "headlines": [
    {
      "title": "Adani Ports remains steady (-0.87%) in recent trading",
      "source": "ZORO AI",
      "time": "2025-10-17T19:07:45.572842"
    },
    {
      "title": "Wipro remains steady (-0.75%) in recent trading",
      "source": "ZORO AI",
      "time": "2025-10-17T19:07:46.173513"
    },
    {
      "title": "Reliance remains steady (-1.84%) in recent trading",
      "source": "ZORO AI",
      "time": "2025-10-17T19:07:46.402234"
    },
    {
      "title": "Tata Motors faces regulatory pipeline delays",
      "source": "ZORO AI",
      "time": "2025-10-17T19:07:46.402253"
    },
    {
      "title": "Reliance faces regulatory pipeline delays",
      "source": "ZORO AI",
      "time": "2025-10-17T19:07:46.402259"
    },
    {
      "title": "Infosys announces merger deal",
      "source": "ZORO AI",
      "time": "2025-10-17T19:07:46.402264"
    },
    {
      "title": "Infosys launches new product line",
      "source": "ZORO AI",
      "time": "2025-10-17T19:07:46.402272"
    },
    {
      "title": "Wipro launches new product line",
      "source": "ZORO AI",
      "time": "2025-10-17T19:07:46.402277"
    },
    {
      "title": "Reliance faces regulatory pipeline delays",
      "source": "ZORO AI",
      "time": "2025-10-17T19:07:46.402283"
    },
    {
      "title": "Wipro announces merger deal",
      "source": "ZORO AI",
      "time": "2025-10-17T19:07:46.402287"
    }
  ]
}