{
  "updated": "2026-01-17T13:52:18.616103",
  "headlines": [
    {
      "title": "Adani Ports shares plunge -5.89% amid market sell\u2011off",
      "source": "ZORO AI",
      "time": "2026-01-17T13:52:18.120168"
    },
    {
      "title": "Infosys remains steady (-1.01%) in recent trading",
      "source": "ZORO AI",
      "time": "2026-01-17T13:52:18.266483"
    },
    {
      "title": "Wipro shares plunge -7.41% amid market sell\u2011off",
      "source": "ZORO AI",
      "time": "2026-01-17T13:52:18.467619"
    },
    {
      "title": "Reliance remains steady (-2.12%) in recent trading",
      "source": "ZORO AI",
      "time": "2026-01-17T13:52:18.616041"
    },
    {
      "title": "Wipro faces regulatory pipeline delays",
      "source": "ZORO AI",
      "time": "2026-01-17T13:52:18.616065"
    },
    {
      "title": "Adani Ports announces merger deal",
      "source": "ZORO AI",
      "time": "2026-01-17T13:52:18.616074"
    },
    {
      "title": "Infosys launches new product line",
      "source": "ZORO AI",
      "time": "2026-01-17T13:52:18.616080"
    },
    {
      "title": "Infosys faces regulatory pipeline delays",
      "source": "ZORO AI",
      "time": "2026-01-17T13:52:18.616089"
    },
    {
      "title": "Infosys faces regulatory pipeline delays",
      "source": "ZORO AI",
      "time": "2026-01-17T13:52:18.616095"
    },
    {
      "title": "Infosys launches new product line",
      "source": "ZORO AI",
      "time": "2026-01-17T13:52:18.616100"
    }
  ]
}