{
  "updated": "2025-11-14T05:14:06.959869",
  "headlines": [
    {
      "title": "Adani Ports remains steady (+0.24%) in recent trading",
      "source": "ZORO AI",
      "time": "2025-11-14T05:14:06.581390"
    },
    {
      "title": "Infosys remains steady (-0.76%) in recent trading",
      "source": "ZORO AI",
      "time": "2025-11-14T05:14:06.728443"
    },
    {
      "title": "Wipro remains steady (+0.00%) in recent trading",
      "source": "ZORO AI",
      "time": "2025-11-14T05:14:06.875990"
    },
    {
      "title": "Reliance shares plunge -6.79% amid market sell\u2011off",
      "source": "ZORO AI",
      "time": "2025-11-14T05:14:06.959816"
    },
    {
      "title": "Infosys launches new product line",
      "source": "ZORO AI",
      "time": "2025-11-14T05:14:06.959837"
    },
    {
      "title": "Tata Motors faces regulatory pipeline delays",
      "source": "ZORO AI",
      "time": "2025-11-14T05:14:06.959842"
    },
    {
      "title": "Adani Ports announces merger deal",
      "source": "ZORO AI",
      "time": "2025-11-14T05:14:06.959847"
    },
    {
      "title": "Adani Ports announces merger deal",
      "source": "ZORO AI",
      "time": "2025-11-14T05:14:06.959855"
    },
    {
      "title": "Wipro announces merger deal",
      "source": "ZORO AI",
      "time": "2025-11-14T05:14:06.959861"
    },
    {
      "title": "Reliance announces merger deal",
      "source": "ZORO AI",
      "time": "2025-11-14T05:14:06.959866"
    }
  ]
}