{
  "updated": "2025-11-12T14:41:34.244689",
  "headlines": [
    {
      "title": "Adani Ports remains steady (+1.70%) in recent trading",
      "source": "ZORO AI",
      "time": "2025-11-12T14:41:33.792335"
    },
    {
      "title": "Infosys remains steady (+1.41%) in recent trading",
      "source": "ZORO AI",
      "time": "2025-11-12T14:41:33.996105"
    },
    {
      "title": "Wipro remains steady (+0.37%) in recent trading",
      "source": "ZORO AI",
      "time": "2025-11-12T14:41:34.157704"
    },
    {
      "title": "Reliance remains steady (+1.02%) in recent trading",
      "source": "ZORO AI",
      "time": "2025-11-12T14:41:34.244638"
    },
    {
      "title": "Reliance announces merger deal",
      "source": "ZORO AI",
      "time": "2025-11-12T14:41:34.244655"
    },
    {
      "title": "Adani Ports announces merger deal",
      "source": "ZORO AI",
      "time": "2025-11-12T14:41:34.244661"
    },
    {
      "title": "Adani Ports faces regulatory pipeline delays",
      "source": "ZORO AI",
      "time": "2025-11-12T14:41:34.244666"
    },
    {
      "title": "Infosys faces regulatory pipeline delays",
      "source": "ZORO AI",
      "time": "2025-11-12T14:41:34.244676"
    },
    {
      "title": "Tata Motors faces regulatory pipeline delays",
      "source": "ZORO AI",
      "time": "2025-11-12T14:41:34.244681"
    },
    {
      "title": "Infosys announces merger deal",
      "source": "ZORO AI",
      "time": "2025-11-12T14:41:34.244687"
    }
  ]
}