{
  "updated": "2026-01-15T20:56:23.367541",
  "headlines": [
    {
      "title": "Infosys remains steady (-2.76%) in recent trading",
      "source": "ZORO AI",
      "time": "2026-01-15T20:56:23.140521"
    },
    {
      "title": "Wipro remains steady (-1.98%) in recent trading",
      "source": "ZORO AI",
      "time": "2026-01-15T20:56:23.292227"
    },
    {
      "title": "Reliance remains steady (-2.06%) in recent trading",
      "source": "ZORO AI",
      "time": "2026-01-15T20:56:23.367488"
    },
    {
      "title": "Reliance announces merger deal",
      "source": "ZORO AI",
      "time": "2026-01-15T20:56:23.367503"
    },
    {
      "title": "Tata Motors launches new product line",
      "source": "ZORO AI",
      "time": "2026-01-15T20:56:23.367508"
    },
    {
      "title": "Tata Motors launches new product line",
      "source": "ZORO AI",
      "time": "2026-01-15T20:56:23.367511"
    },
    {
      "title": "Infosys launches new product line",
      "source": "ZORO AI",
      "time": "2026-01-15T20:56:23.367516"
    },
    {
      "title": "Adani Ports launches new product line",
      "source": "ZORO AI",
      "time": "2026-01-15T20:56:23.367527"
    },
    {
      "title": "Reliance faces regulatory pipeline delays",
      "source": "ZORO AI",
      "time": "2026-01-15T20:56:23.367532"
    },
    {
      "title": "Wipro faces regulatory pipeline delays",
      "source": "ZORO AI",
      "time": "2026-01-15T20:56:23.367538"
    }
  ]
}