{
  "updated": "2025-11-12T19:58:15.951492",
  "headlines": [
    {
      "title": "Adani Ports shares soar 4.74% on strong market performance",
      "source": "ZORO AI",
      "time": "2025-11-12T19:58:15.536900"
    },
    {
      "title": "Infosys remains steady (+0.50%) in recent trading",
      "source": "ZORO AI",
      "time": "2025-11-12T19:58:15.697389"
    },
    {
      "title": "Reliance remains steady (+1.84%) in recent trading",
      "source": "ZORO AI",
      "time": "2025-11-12T19:58:15.951437"
    },
    {
      "title": "Infosys launches new product line",
      "source": "ZORO AI",
      "time": "2025-11-12T19:58:15.951457"
    },
    {
      "title": "Infosys announces merger deal",
      "source": "ZORO AI",
      "time": "2025-11-12T19:58:15.951464"
    },
    {
      "title": "Infosys faces regulatory pipeline delays",
      "source": "ZORO AI",
      "time": "2025-11-12T19:58:15.951467"
    },
    {
      "title": "Infosys launches new product line",
      "source": "ZORO AI",
      "time": "2025-11-12T19:58:15.951472"
    },
    {
      "title": "Adani Ports announces merger deal",
      "source": "ZORO AI",
      "time": "2025-11-12T19:58:15.951478"
    },
    {
      "title": "Infosys faces regulatory pipeline delays",
      "source": "ZORO AI",
      "time": "2025-11-12T19:58:15.951484"
    },
    {
      "title": "Tata Motors announces merger deal",
      "source": "ZORO AI",
      "time": "2025-11-12T19:58:15.951489"
    }
  ]
}