{
  "updated": "2025-12-07T06:18:30.989500",
  "headlines": [
    {
      "title": "Adani Ports remains steady (-2.37%) in recent trading",
      "source": "ZORO AI",
      "time": "2025-12-07T06:18:30.599797"
    },
    {
      "title": "Infosys remains steady (-1.20%) in recent trading",
      "source": "ZORO AI",
      "time": "2025-12-07T06:18:30.764575"
    },
    {
      "title": "Wipro remains steady (+1.06%) in recent trading",
      "source": "ZORO AI",
      "time": "2025-12-07T06:18:30.908667"
    },
    {
      "title": "Reliance remains steady (-1.49%) in recent trading",
      "source": "ZORO AI",
      "time": "2025-12-07T06:18:30.989466"
    },
    {
      "title": "Infosys faces regulatory pipeline delays",
      "source": "ZORO AI",
      "time": "2025-12-07T06:18:30.989480"
    },
    {
      "title": "Adani Ports faces regulatory pipeline delays",
      "source": "ZORO AI",
      "time": "2025-12-07T06:18:30.989485"
    },
    {
      "title": "Tata Motors launches new product line",
      "source": "ZORO AI",
      "time": "2025-12-07T06:18:30.989488"
    },
    {
      "title": "Adani Ports faces regulatory pipeline delays",
      "source": "ZORO AI",
      "time": "2025-12-07T06:18:30.989493"
    },
    {
      "title": "Tata Motors faces regulatory pipeline delays",
      "source": "ZORO AI",
      "time": "2025-12-07T06:18:30.989496"
    },
    {
      "title": "Reliance announces merger deal",
      "source": "ZORO AI",
      "time": "2025-12-07T06:18:30.989499"
    }
  ]
}