{
  "updated": "2025-06-28T20:12:22.769629",
  "headlines": [
    {
      "title": "Adani Ports remains steady (+0.05%) in recent trading",
      "source": "ZORO AI",
      "time": "2025-06-28T20:12:22.326243"
    },
    {
      "title": "Infosys remains steady (-0.43%) in recent trading",
      "source": "ZORO AI",
      "time": "2025-06-28T20:12:22.507807"
    },
    {
      "title": "Wipro remains steady (-1.62%) in recent trading",
      "source": "ZORO AI",
      "time": "2025-06-28T20:12:22.667852"
    },
    {
      "title": "Reliance shares plunge -10.46% amid market sell\u2011off",
      "source": "ZORO AI",
      "time": "2025-06-28T20:12:22.769573"
    },
    {
      "title": "Infosys announces merger deal",
      "source": "ZORO AI",
      "time": "2025-06-28T20:12:22.769593"
    },
    {
      "title": "Wipro launches new product line",
      "source": "ZORO AI",
      "time": "2025-06-28T20:12:22.769601"
    },
    {
      "title": "Infosys launches new product line",
      "source": "ZORO AI",
      "time": "2025-06-28T20:12:22.769607"
    },
    {
      "title": "Infosys launches new product line",
      "source": "ZORO AI",
      "time": "2025-06-28T20:12:22.769615"
    },
    {
      "title": "Reliance launches new product line",
      "source": "ZORO AI",
      "time": "2025-06-28T20:12:22.769621"
    },
    {
      "title": "Adani Ports launches new product line",
      "source": "ZORO AI",
      "time": "2025-06-28T20:12:22.769626"
    }
  ]
}