{
  "updated": "2025-12-19T18:55:33.287504",
  "headlines": [
    {
      "title": "Adani Ports remains steady (+0.83%) in recent trading",
      "source": "ZORO AI",
      "time": "2025-12-19T18:55:32.839804"
    },
    {
      "title": "Infosys shares soar 3.75% on strong market performance",
      "source": "ZORO AI",
      "time": "2025-12-19T18:55:33.009642"
    },
    {
      "title": "Wipro shares soar 5.07% on strong market performance",
      "source": "ZORO AI",
      "time": "2025-12-19T18:55:33.196102"
    },
    {
      "title": "Reliance remains steady (+0.85%) in recent trading",
      "source": "ZORO AI",
      "time": "2025-12-19T18:55:33.287466"
    },
    {
      "title": "Tata Motors launches new product line",
      "source": "ZORO AI",
      "time": "2025-12-19T18:55:33.287484"
    },
    {
      "title": "Tata Motors faces regulatory pipeline delays",
      "source": "ZORO AI",
      "time": "2025-12-19T18:55:33.287488"
    },
    {
      "title": "Reliance faces regulatory pipeline delays",
      "source": "ZORO AI",
      "time": "2025-12-19T18:55:33.287492"
    },
    {
      "title": "Reliance launches new product line",
      "source": "ZORO AI",
      "time": "2025-12-19T18:55:33.287496"
    },
    {
      "title": "Tata Motors launches new product line",
      "source": "ZORO AI",
      "time": "2025-12-19T18:55:33.287500"
    },
    {
      "title": "Reliance faces regulatory pipeline delays",
      "source": "ZORO AI",
      "time": "2025-12-19T18:55:33.287502"
    }
  ]
}