{
  "updated": "2025-09-04T21:39:33.221056",
  "headlines": [
    {
      "title": "Adani Ports remains steady (+0.78%) in recent trading",
      "source": "ZORO AI",
      "time": "2025-09-04T21:39:32.830207"
    },
    {
      "title": "Infosys remains steady (-0.30%) in recent trading",
      "source": "ZORO AI",
      "time": "2025-09-04T21:39:32.969606"
    },
    {
      "title": "Wipro remains steady (-1.44%) in recent trading",
      "source": "ZORO AI",
      "time": "2025-09-04T21:39:33.121647"
    },
    {
      "title": "Reliance shares plunge -3.44% amid market sell\u2011off",
      "source": "ZORO AI",
      "time": "2025-09-04T21:39:33.221021"
    },
    {
      "title": "Infosys faces regulatory pipeline delays",
      "source": "ZORO AI",
      "time": "2025-09-04T21:39:33.221036"
    },
    {
      "title": "Adani Ports announces merger deal",
      "source": "ZORO AI",
      "time": "2025-09-04T21:39:33.221040"
    },
    {
      "title": "Adani Ports faces regulatory pipeline delays",
      "source": "ZORO AI",
      "time": "2025-09-04T21:39:33.221044"
    },
    {
      "title": "Reliance faces regulatory pipeline delays",
      "source": "ZORO AI",
      "time": "2025-09-04T21:39:33.221049"
    },
    {
      "title": "Wipro launches new product line",
      "source": "ZORO AI",
      "time": "2025-09-04T21:39:33.221052"
    },
    {
      "title": "Infosys announces merger deal",
      "source": "ZORO AI",
      "time": "2025-09-04T21:39:33.221055"
    }
  ]
}