{
  "updated": "2026-01-15T21:59:20.173135",
  "headlines": [
    {
      "title": "Adani Ports remains steady (-0.81%) in recent trading",
      "source": "ZORO AI",
      "time": "2026-01-15T21:59:19.841866"
    },
    {
      "title": "Infosys remains steady (-2.74%) in recent trading",
      "source": "ZORO AI",
      "time": "2026-01-15T21:59:19.968464"
    },
    {
      "title": "Wipro remains steady (-1.98%) in recent trading",
      "source": "ZORO AI",
      "time": "2026-01-15T21:59:20.093472"
    },
    {
      "title": "Reliance remains steady (+0.00%) in recent trading",
      "source": "ZORO AI",
      "time": "2026-01-15T21:59:20.173082"
    },
    {
      "title": "Infosys announces merger deal",
      "source": "ZORO AI",
      "time": "2026-01-15T21:59:20.173101"
    },
    {
      "title": "Adani Ports launches new product line",
      "source": "ZORO AI",
      "time": "2026-01-15T21:59:20.173110"
    },
    {
      "title": "Adani Ports announces merger deal",
      "source": "ZORO AI",
      "time": "2026-01-15T21:59:20.173116"
    },
    {
      "title": "Reliance launches new product line",
      "source": "ZORO AI",
      "time": "2026-01-15T21:59:20.173121"
    },
    {
      "title": "Reliance announces merger deal",
      "source": "ZORO AI",
      "time": "2026-01-15T21:59:20.173124"
    },
    {
      "title": "Reliance launches new product line",
      "source": "ZORO AI",
      "time": "2026-01-15T21:59:20.173127"
    }
  ]
}