{
  "updated": "2025-11-14T06:47:22.735069",
  "headlines": [
    {
      "title": "Adani Ports remains steady (+0.24%) in recent trading",
      "source": "ZORO AI",
      "time": "2025-11-14T06:47:21.820248"
    },
    {
      "title": "Infosys remains steady (-0.76%) in recent trading",
      "source": "ZORO AI",
      "time": "2025-11-14T06:47:22.114979"
    },
    {
      "title": "Wipro remains steady (+0.00%) in recent trading",
      "source": "ZORO AI",
      "time": "2025-11-14T06:47:22.461378"
    },
    {
      "title": "Reliance shares plunge -6.83% amid market sell\u2011off",
      "source": "ZORO AI",
      "time": "2025-11-14T06:47:22.735013"
    },
    {
      "title": "Reliance faces regulatory pipeline delays",
      "source": "ZORO AI",
      "time": "2025-11-14T06:47:22.735034"
    },
    {
      "title": "Tata Motors announces merger deal",
      "source": "ZORO AI",
      "time": "2025-11-14T06:47:22.735043"
    },
    {
      "title": "Wipro launches new product line",
      "source": "ZORO AI",
      "time": "2025-11-14T06:47:22.735049"
    },
    {
      "title": "Adani Ports announces merger deal",
      "source": "ZORO AI",
      "time": "2025-11-14T06:47:22.735058"
    },
    {
      "title": "Adani Ports launches new product line",
      "source": "ZORO AI",
      "time": "2025-11-14T06:47:22.735063"
    },
    {
      "title": "Adani Ports launches new product line",
      "source": "ZORO AI",
      "time": "2025-11-14T06:47:22.735067"
    }
  ]
}