{
  "updated": "2025-11-10T21:43:18.519566",
  "headlines": [
    {
      "title": "Adani Ports remains steady (+0.51%) in recent trading",
      "source": "ZORO AI",
      "time": "2025-11-10T21:43:18.109592"
    },
    {
      "title": "Infosys remains steady (+1.58%) in recent trading",
      "source": "ZORO AI",
      "time": "2025-11-10T21:43:18.274444"
    },
    {
      "title": "Wipro remains steady (+0.77%) in recent trading",
      "source": "ZORO AI",
      "time": "2025-11-10T21:43:18.424605"
    },
    {
      "title": "Reliance remains steady (-1.92%) in recent trading",
      "source": "ZORO AI",
      "time": "2025-11-10T21:43:18.519495"
    },
    {
      "title": "Reliance announces merger deal",
      "source": "ZORO AI",
      "time": "2025-11-10T21:43:18.519515"
    },
    {
      "title": "Tata Motors announces merger deal",
      "source": "ZORO AI",
      "time": "2025-11-10T21:43:18.519522"
    },
    {
      "title": "Reliance faces regulatory pipeline delays",
      "source": "ZORO AI",
      "time": "2025-11-10T21:43:18.519528"
    },
    {
      "title": "Wipro announces merger deal",
      "source": "ZORO AI",
      "time": "2025-11-10T21:43:18.519536"
    },
    {
      "title": "Adani Ports launches new product line",
      "source": "ZORO AI",
      "time": "2025-11-10T21:43:18.519542"
    },
    {
      "title": "Adani Ports faces regulatory pipeline delays",
      "source": "ZORO AI",
      "time": "2025-11-10T21:43:18.519563"
    }
  ]
}