{
  "updated": "2025-10-02T09:43:40.818152",
  "headlines": [
    {
      "title": "Adani Ports remains steady (+1.33%) in recent trading",
      "source": "ZORO AI",
      "time": "2025-10-02T09:43:40.489438"
    },
    {
      "title": "Infosys remains steady (+0.61%) in recent trading",
      "source": "ZORO AI",
      "time": "2025-10-02T09:43:40.606476"
    },
    {
      "title": "Wipro remains steady (+0.00%) in recent trading",
      "source": "ZORO AI",
      "time": "2025-10-02T09:43:40.745269"
    },
    {
      "title": "Reliance remains steady (+0.87%) in recent trading",
      "source": "ZORO AI",
      "time": "2025-10-02T09:43:40.818101"
    },
    {
      "title": "Infosys announces merger deal",
      "source": "ZORO AI",
      "time": "2025-10-02T09:43:40.818120"
    },
    {
      "title": "Tata Motors announces merger deal",
      "source": "ZORO AI",
      "time": "2025-10-02T09:43:40.818125"
    },
    {
      "title": "Tata Motors faces regulatory pipeline delays",
      "source": "ZORO AI",
      "time": "2025-10-02T09:43:40.818130"
    },
    {
      "title": "Infosys launches new product line",
      "source": "ZORO AI",
      "time": "2025-10-02T09:43:40.818137"
    },
    {
      "title": "Infosys announces merger deal",
      "source": "ZORO AI",
      "time": "2025-10-02T09:43:40.818144"
    },
    {
      "title": "Infosys faces regulatory pipeline delays",
      "source": "ZORO AI",
      "time": "2025-10-02T09:43:40.818149"
    }
  ]
}